bibl/__init__.py
bibl/combinatorics/__init__.py
bibl/combinatorics/core.py
bibl/diffeq/__init__.py
bibl/diffeq/core.py
tests/__init__.py
tests/test_combinatorics.py
tests/test_diffeq.py
bibl_vikauustin-0.1.0.dist-info/METADATA
bibl_vikauustin-0.1.0.dist-info/WHEEL
bibl_vikauustin-0.1.0.dist-info/top_level.txt
bibl_vikauustin-0.1.0.dist-info/RECORD
