Metadata-Version: 2.4
Name: bibl-vikauustin
Version: 0.1.0
Summary: Библиотека для комбинаторных вычислений и численного решения ОДУ
Author: Виктория
Author-email: Виктория <vktrstnv65@bk.ru>
License: MIT
Project-URL: Homepage, https://github.com/vikauustin/library
Project-URL: Issues, https://github.com/vikauustin/library/issues
Classifier: Programming Language :: Python :: 3
Classifier: License :: OSI Approved :: MIT License
Classifier: Operating System :: OS Independent
Requires-Python: >=3.7
Dynamic: author
Dynamic: requires-python
